{
  "meta": {
    "generated_utc": "2026-02-25T16:13:49.693131+00:00",
    "generated_et": "2026-02-25 11:13:49 ET",
    "ticker_count": 52,
    "version": "1.1"
  },
  "signals": {
    "playbook": {
      "GLD_RSI_gt_79": {
        "value": 59.7,
        "threshold": 79,
        "active": false
      },
      "USDU_RSI_lt_25": {
        "value": 50.7,
        "threshold": 25,
        "active": false
      },
      "XLP_RSI_gt_65": {
        "value": 64.5,
        "threshold": 65,
        "active": false
      },
      "XLP_RSI_gt_75": {
        "value": 64.5,
        "threshold": 75,
        "active": false
      },
      "SPY_RSI_gt_79": {
        "value": 54.9,
        "threshold": 79,
        "active": false
      },
      "QQQ_RSI_gt_79": {
        "value": 54.4,
        "threshold": 79,
        "active": false
      },
      "SMH_RSI_gt_79": {
        "value": 67.1,
        "threshold": 79,
        "active": false
      },
      "XLF_RSI_gt_70": {
        "value": 40.2,
        "threshold": 70,
        "active": false
      },
      "UVXY_RSI_gt_82": {
        "value": 47.8,
        "threshold": 82,
        "active": false
      },
      "VIXM_RSI_lt_25": {
        "value": 53.0,
        "threshold": 25,
        "active": false
      }
    },
    "combos": {
      "double_signal": {
        "active": false,
        "desc": "GLD>79+USDU<25 \u2192 TQQQ"
      },
      "triple_signal": {
        "active": false,
        "desc": "Double+XLP>65 \u2192 TQQQ high conviction"
      },
      "xlp_cascade": {
        "active": false,
        "desc": "XLP>75 \u2192 UVXY 1-day hold"
      }
    },
    "bond_momentum": {
      "direction": "RISING",
      "tlt_ret_10d": 1.51,
      "bnd_ret_10d": 0.6,
      "uvxy_conviction": "MODERATE"
    },
    "smh_levels": {
      "price": 425.24,
      "sma200": 324.68,
      "pct_above": 31.0,
      "trim": 422.08,
      "warn": 438.32,
      "sell": 454.55
    },
    "contrarian": {
      "FAS": {
        "rsi10": 38.5,
        "below_sma200": true,
        "bear_ema": true,
        "status": "ACTIVE"
      },
      "TECL": {
        "rsi10": 51.9,
        "below_sma200": false,
        "bear_ema": true,
        "status": "INACTIVE"
      },
      "FNGO": {
        "rsi10": 43.9,
        "below_sma200": true,
        "bear_ema": true,
        "status": "WATCH"
      },
      "LABU": {
        "rsi10": 58.5,
        "below_sma200": false,
        "bear_ema": false,
        "status": "INACTIVE"
      },
      "NAIL": {
        "rsi10": 37.2,
        "below_sma200": true,
        "bear_ema": false,
        "status": "ACTIVE"
      }
    },
    "extended": {
      "SOXL": {
        "vs_sma200": 92.5,
        "rsi10": 64.4,
        "warning": "ELEVATED"
      },
      "KORU": {
        "vs_sma200": 296.4,
        "rsi10": 80.1,
        "warning": "EXTENDED"
      },
      "EDC": {
        "vs_sma200": 63.9,
        "rsi10": 70.3,
        "warning": "ELEVATED"
      },
      "LABU": {
        "vs_sma200": 66.7,
        "rsi10": 58.5,
        "warning": "ELEVATED"
      }
    },
    "natgas": {
      "signal": "\ud83d\udfe2 BOIL BUY",
      "action": "Enter BOIL (cold forecast + oversold)",
      "boil": {
        "price": 16.89,
        "rsi10": 38.6,
        "gain_5d": -3.0,
        "gain_7d": -11.0,
        "signal": "ACTIVE",
        "reasoning": [
          "Winter + RSI 38.6 < 50 + 7d temp drop -14.3\u00b0F \u2192 BUY BOIL"
        ]
      },
      "kold": {
        "price": 22.74,
        "rsi10": 50.9,
        "signal": "INACTIVE",
        "tier": null,
        "reasoning": [],
        "weather_override": false
      },
      "macro_filters": {
        "uco_rsi": 58.4,
        "uco_enhanced": true,
        "uvxy_rsi": 47.8,
        "usdu_rsi": 50.7,
        "supply_shock": false
      },
      "weather": {
        "current_temp": 30.8,
        "temp_change_7d": -14.3,
        "severe_cold": true,
        "is_winter": true
      },
      "thresholds": {
        "30pct_5d": {
          "win_rate": "88%",
          "avg_return": "+14.5%",
          "n": 24
        },
        "40pct_5d": {
          "win_rate": "89%",
          "avg_return": "+18.5%",
          "n": 9
        },
        "50pct_5d": {
          "win_rate": "100%",
          "avg_return": "+25.4%",
          "n": 7
        }
      }
    },
    "active_alerts": [
      "BOIL BUY: cold forecast + oversold",
      "FAS CONTRARIAN: RSI<40+below SMA200",
      "FNGO WATCH: below SMA200, nearing oversold",
      "NAIL CONTRARIAN: RSI<40+below SMA200",
      "SOXL ELEVATED: +92% above SMA200",
      "KORU EXTENDED: +296% above SMA200",
      "EDC ELEVATED: +64% above SMA200",
      "LABU ELEVATED: +67% above SMA200"
    ]
  },
  "indicators": {
    "SPY": {
      "price": 691.12,
      "change_pct": 0.55,
      "rsi10": 54.9,
      "ema9": 687.14,
      "ema20": 687.51,
      "ema50": 685.48,
      "ema200": 652.71,
      "sma50": 687.29,
      "sma200": 650.54,
      "ema_cross": "BEAR",
      "above_sma200": true,
      "vs_sma200": 6.2,
      "vs_sma50": 0.6,
      "ret_1d": 0.55,
      "ret_5d": 0.7,
      "ret_10d": -0.14,
      "ret_20d": -0.63
    },
    "QQQ": {
      "price": 614.27,
      "change_pct": 1.05,
      "rsi10": 54.4,
      "ema9": 607.85,
      "ema20": 610.24,
      "ema50": 613.04,
      "ema200": 584.47,
      "sma50": 615.83,
      "sma200": 584.59,
      "ema_cross": "BEAR",
      "above_sma200": true,
      "vs_sma200": 5.1,
      "vs_sma50": -0.3,
      "ret_1d": 1.05,
      "ret_5d": 1.4,
      "ret_10d": 0.46,
      "ret_20d": -2.67
    },
    "SMH": {
      "price": 425.24,
      "change_pct": 1.45,
      "rsi10": 67.1,
      "ema9": 414.29,
      "ema20": 407.76,
      "ema50": 391.93,
      "ema200": 335.35,
      "sma50": 388.93,
      "sma200": 324.68,
      "ema_cross": "BULL",
      "above_sma200": true,
      "vs_sma200": 31.0,
      "vs_sma50": 9.3,
      "ret_1d": 1.45,
      "ret_5d": 3.08,
      "ret_10d": 5.06,
      "ret_20d": 4.42
    },
    "IWM": {
      "price": 263.01,
      "change_pct": -0.12,
      "rsi10": 50.6,
      "ema9": 263.09,
      "ema20": 262.7,
      "ema50": 258.87,
      "ema200": 240.78,
      "sma50": 259.07,
      "sma200": 236.28,
      "ema_cross": "BULL",
      "above_sma200": true,
      "vs_sma200": 11.3,
      "vs_sma50": 1.5,
      "ret_1d": -0.12,
      "ret_5d": -0.37,
      "ret_10d": -1.18,
      "ret_20d": -0.65
    },
    "XLP": {
      "price": 88.92,
      "change_pct": -0.92,
      "rsi10": 64.5,
      "ema9": 88.47,
      "ema20": 87.01,
      "ema50": 83.85,
      "ema200": 80.17,
      "sma50": 82.6,
      "sma200": 79.81,
      "ema_cross": "BULL",
      "above_sma200": true,
      "vs_sma200": 11.4,
      "vs_sma50": 7.6,
      "ret_1d": -0.92,
      "ret_5d": 0.99,
      "ret_10d": 2.03,
      "ret_20d": 6.92
    },
    "XLU": {
      "price": 47.15,
      "change_pct": -0.11,
      "rsi10": 76.8,
      "ema9": 46.23,
      "ema20": 45.2,
      "ema50": 44.18,
      "ema200": 42.39,
      "sma50": 43.56,
      "sma200": 42.5,
      "ema_cross": "BULL",
      "above_sma200": true,
      "vs_sma200": 10.9,
      "vs_sma50": 8.2,
      "ret_1d": -0.11,
      "ret_5d": 3.38,
      "ret_10d": 6.67,
      "ret_20d": 8.57
    },
    "XLV": {
      "price": 158.09,
      "change_pct": 0.14,
      "rsi10": 57.1,
      "ema9": 157.47,
      "ema20": 156.91,
      "ema50": 155.41,
      "ema200": 147.22,
      "sma50": 156.18,
      "sma200": 142.71,
      "ema_cross": "BULL",
      "above_sma200": true,
      "vs_sma200": 10.8,
      "vs_sma50": 1.2,
      "ret_1d": 0.14,
      "ret_5d": 0.27,
      "ret_10d": 1.78,
      "ret_20d": 1.7
    },
    "XLF": {
      "price": 51.49,
      "change_pct": 1.01,
      "rsi10": 40.2,
      "ema9": 51.87,
      "ema20": 52.54,
      "ema50": 53.21,
      "ema200": 52.19,
      "sma50": 53.94,
      "sma200": 52.58,
      "ema_cross": "BEAR",
      "above_sma200": false,
      "vs_sma200": -2.1,
      "vs_sma50": -4.5,
      "ret_1d": 1.01,
      "ret_5d": -2.08,
      "ret_10d": -3.84,
      "ret_20d": -2.84
    },
    "XLE": {
      "price": 54.47,
      "change_pct": -1.13,
      "rsi10": 61.8,
      "ema9": 54.49,
      "ema20": 53.15,
      "ema50": 50.2,
      "ema200": 45.74,
      "sma50": 48.98,
      "sma200": 44.51,
      "ema_cross": "BULL",
      "above_sma200": true,
      "vs_sma200": 22.4,
      "vs_sma50": 11.2,
      "ret_1d": -1.13,
      "ret_5d": -0.56,
      "ret_10d": 1.67,
      "ret_20d": 9.67
    },
    "GLD": {
      "price": 477.46,
      "change_pct": 0.6,
      "rsi10": 59.7,
      "ema9": 468.36,
      "ema20": 460.31,
      "ema50": 438.77,
      "ema200": 371.97,
      "sma50": 435.54,
      "sma200": 360.45,
      "ema_cross": "BULL",
      "above_sma200": true,
      "vs_sma200": 32.5,
      "vs_sma50": 9.6,
      "ret_1d": 0.6,
      "ret_5d": 4.19,
      "ret_10d": 3.26,
      "ret_20d": 0.29
    },
    "TLT": {
      "price": 89.87,
      "change_pct": -0.03,
      "rsi10": 68.0,
      "ema9": 89.44,
      "ema20": 88.77,
      "ema50": 88.16,
      "ema200": 87.24,
      "sma50": 87.72,
      "sma200": 86.55,
      "ema_cross": "BULL",
      "above_sma200": true,
      "vs_sma200": 3.8,
      "vs_sma50": 2.5,
      "ret_1d": -0.03,
      "ret_5d": 0.38,
      "ret_10d": 1.51,
      "ret_20d": 2.75
    },
    "HYG": {
      "price": 80.88,
      "change_pct": 0.08,
      "rsi10": 55.3,
      "ema9": 80.86,
      "ema20": 80.8,
      "ema50": 80.51,
      "ema200": 78.73,
      "sma50": 80.54,
      "sma200": 78.77,
      "ema_cross": "BULL",
      "above_sma200": true,
      "vs_sma200": 2.7,
      "vs_sma50": 0.4,
      "ret_1d": 0.08,
      "ret_5d": -0.04,
      "ret_10d": 0.04,
      "ret_20d": 0.13
    },
    "LQD": {
      "price": 111.66,
      "change_pct": -0.02,
      "rsi10": 69.7,
      "ema9": 111.49,
      "ema20": 111.11,
      "ema50": 110.58,
      "ema200": 108.5,
      "sma50": 110.4,
      "sma200": 108.28,
      "ema_cross": "BULL",
      "above_sma200": true,
      "vs_sma200": 3.1,
      "vs_sma50": 1.1,
      "ret_1d": -0.02,
      "ret_5d": 0.06,
      "ret_10d": 0.76,
      "ret_20d": 1.14
    },
    "TMV": {
      "price": 34.03,
      "change_pct": 0.09,
      "rsi10": 33.9,
      "ema9": 34.49,
      "ema20": 35.21,
      "ema50": 35.71,
      "ema200": 35.85,
      "sma50": 36.26,
      "sma200": 36.59,
      "ema_cross": "BEAR",
      "above_sma200": false,
      "vs_sma200": -7.0,
      "vs_sma50": -6.1,
      "ret_1d": 0.09,
      "ret_5d": -0.9,
      "ret_10d": -3.98,
      "ret_20d": -7.07
    },
    "USDU": {
      "price": 25.61,
      "change_pct": -0.08,
      "rsi10": 50.7,
      "ema9": 25.6,
      "ema20": 25.6,
      "ema50": 25.67,
      "ema200": 25.63,
      "sma50": 25.7,
      "sma200": 25.51,
      "ema_cross": "BULL",
      "above_sma200": true,
      "vs_sma200": 0.4,
      "vs_sma50": -0.4,
      "ret_1d": -0.08,
      "ret_5d": -0.08,
      "ret_10d": 0.87,
      "ret_20d": 1.59
    },
    "BND": {
      "price": 74.92,
      "change_pct": -0.02,
      "rsi10": 71.4,
      "ema9": 74.79,
      "ema20": 74.55,
      "ema50": 74.21,
      "ema200": 72.94,
      "sma50": 74.12,
      "sma200": 72.79,
      "ema_cross": "BULL",
      "above_sma200": true,
      "vs_sma200": 2.9,
      "vs_sma50": 1.1,
      "ret_1d": -0.02,
      "ret_5d": 0.17,
      "ret_10d": 0.6,
      "ret_20d": 1.19
    },
    "UCO": {
      "price": 24.42,
      "change_pct": -2.57,
      "rsi10": 58.4,
      "ema9": 24.27,
      "ema20": 23.49,
      "ema50": 22.26,
      "ema200": 22.41,
      "sma50": 21.4,
      "sma200": 22.12,
      "ema_cross": "BULL",
      "above_sma200": true,
      "vs_sma200": 10.4,
      "vs_sma50": 14.1,
      "ret_1d": -2.57,
      "ret_5d": 1.22,
      "ret_10d": 3.5,
      "ret_20d": 9.28
    },
    "BOIL": {
      "price": 16.89,
      "change_pct": 4.1,
      "rsi10": 38.6,
      "ema9": 17.82,
      "ema20": 19.81,
      "ema50": 22.95,
      "ema200": 34.1,
      "sma50": 22.31,
      "sma200": 34.35,
      "ema_cross": "BEAR",
      "above_sma200": false,
      "vs_sma200": -50.8,
      "vs_sma50": -24.3,
      "ret_1d": 4.1,
      "ret_5d": -2.96,
      "ret_10d": -8.58,
      "ret_20d": -45.83
    },
    "DBC": {
      "price": 24.73,
      "change_pct": 0.04,
      "rsi10": 61.5,
      "ema9": 24.46,
      "ema20": 24.21,
      "ema50": 23.63,
      "ema200": 22.34,
      "sma50": 23.45,
      "sma200": 22.04,
      "ema_cross": "BULL",
      "above_sma200": true,
      "vs_sma200": 12.2,
      "vs_sma50": 5.4,
      "ret_1d": 0.04,
      "ret_5d": 2.15,
      "ret_10d": 2.44,
      "ret_20d": 0.45
    },
    "UVXY": {
      "price": 37.56,
      "change_pct": -3.07,
      "rsi10": 47.8,
      "ema9": 38.69,
      "ema20": 38.19,
      "ema50": 39.67,
      "ema200": 62.64,
      "sma50": 37.39,
      "sma200": 64.04,
      "ema_cross": "BULL",
      "above_sma200": false,
      "vs_sma200": -41.4,
      "vs_sma50": 0.4,
      "ret_1d": -3.07,
      "ret_5d": -2.37,
      "ret_10d": 3.53,
      "ret_20d": 3.61
    },
    "SVXY": {
      "price": 53.34,
      "change_pct": 1.1,
      "rsi10": 50.3,
      "ema9": 52.9,
      "ema20": 53.33,
      "ema50": 53.32,
      "ema200": 50.35,
      "sma50": 54.26,
      "sma200": 48.47,
      "ema_cross": "BEAR",
      "above_sma200": true,
      "vs_sma200": 10.1,
      "vs_sma50": -1.7,
      "ret_1d": 1.1,
      "ret_5d": 0.74,
      "ret_10d": -1.53,
      "ret_20d": -2.31
    },
    "VIXY": {
      "price": 26.92,
      "change_pct": -2.37,
      "rsi10": 48.3,
      "ema9": 27.44,
      "ema20": 27.14,
      "ema50": 27.59,
      "ema200": 34.81,
      "sma50": 26.58,
      "sma200": 36.34,
      "ema_cross": "BULL",
      "above_sma200": false,
      "vs_sma200": -25.9,
      "vs_sma50": 1.3,
      "ret_1d": -2.37,
      "ret_5d": -1.63,
      "ret_10d": 2.22,
      "ret_20d": 3.2
    },
    "VIXM": {
      "price": 15.47,
      "change_pct": -0.58,
      "rsi10": 53.0,
      "ema9": 15.48,
      "ema20": 15.39,
      "ema50": 15.42,
      "ema200": 15.83,
      "sma50": 15.24,
      "sma200": 16.16,
      "ema_cross": "BULL",
      "above_sma200": false,
      "vs_sma200": -4.2,
      "vs_sma50": 1.5,
      "ret_1d": -0.58,
      "ret_5d": 0.26,
      "ret_10d": 1.24,
      "ret_20d": 2.25
    },
    "TQQQ": {
      "price": 51.33,
      "change_pct": 3.11,
      "rsi10": 52.9,
      "ema9": 49.9,
      "ema20": 50.72,
      "ema50": 52.01,
      "ema200": 48.24,
      "sma50": 52.7,
      "sma200": 47.78,
      "ema_cross": "BEAR",
      "above_sma200": true,
      "vs_sma200": 7.4,
      "vs_sma50": -2.6,
      "ret_1d": 3.11,
      "ret_5d": 3.93,
      "ret_10d": 0.61,
      "ret_20d": -9.21
    },
    "SOXL": {
      "price": 71.12,
      "change_pct": 3.79,
      "rsi10": 64.4,
      "ema9": 66.8,
      "ema20": 64.22,
      "ema50": 57.85,
      "ema200": 42.22,
      "sma50": 55.94,
      "sma200": 36.96,
      "ema_cross": "BULL",
      "above_sma200": true,
      "vs_sma200": 92.5,
      "vs_sma50": 27.2,
      "ret_1d": 3.79,
      "ret_5d": 7.29,
      "ret_10d": 12.29,
      "ret_20d": 9.49
    },
    "SOXS": {
      "price": 1.6,
      "change_pct": -3.61,
      "rsi10": 34.2,
      "ema9": 1.72,
      "ema20": 1.85,
      "ema50": 2.31,
      "ema200": 6.64,
      "sma50": 2.33,
      "sma200": 5.53,
      "ema_cross": "BEAR",
      "above_sma200": false,
      "vs_sma200": -71.1,
      "vs_sma50": -31.2,
      "ret_1d": -3.61,
      "ret_5d": -6.43,
      "ret_10d": -12.08,
      "ret_20d": -16.23
    },
    "TECL": {
      "price": 109.8,
      "change_pct": 4.88,
      "rsi10": 51.9,
      "ema9": 106.18,
      "ema20": 108.7,
      "ema50": 113.21,
      "ema200": 105.84,
      "sma50": 115.17,
      "sma200": 104.58,
      "ema_cross": "BEAR",
      "above_sma200": true,
      "vs_sma200": 5.0,
      "vs_sma50": -4.7,
      "ret_1d": 4.88,
      "ret_5d": 3.24,
      "ret_10d": -0.87,
      "ret_20d": -12.94
    },
    "FAS": {
      "price": 135.69,
      "change_pct": 3.15,
      "rsi10": 38.5,
      "ema9": 139.33,
      "ema20": 145.65,
      "ema50": 153.03,
      "ema200": 152.41,
      "sma50": 159.62,
      "sma200": 154.71,
      "ema_cross": "BEAR",
      "above_sma200": false,
      "vs_sma200": -12.3,
      "vs_sma50": -15.0,
      "ret_1d": 3.15,
      "ret_5d": -6.7,
      "ret_10d": -12.0,
      "ret_20d": -9.89
    },
    "UPRO": {
      "price": 117.96,
      "change_pct": 1.62,
      "rsi10": 53.3,
      "ema9": 116.18,
      "ema20": 116.76,
      "ema50": 116.77,
      "ema200": 106.48,
      "sma50": 117.69,
      "sma200": 104.64,
      "ema_cross": "BEAR",
      "above_sma200": true,
      "vs_sma200": 12.7,
      "vs_sma50": 0.2,
      "ret_1d": 1.62,
      "ret_5d": 1.89,
      "ret_10d": -1.0,
      "ret_20d": -3.05
    },
    "NAIL": {
      "price": 62.64,
      "change_pct": -11.45,
      "rsi10": 37.2,
      "ema9": 69.87,
      "ema20": 68.92,
      "ema50": 65.35,
      "ema200": 67.54,
      "sma50": 62.65,
      "sma200": 63.28,
      "ema_cross": "BULL",
      "above_sma200": false,
      "vs_sma200": -1.0,
      "vs_sma50": -0.0,
      "ret_1d": -11.45,
      "ret_5d": -16.05,
      "ret_10d": -17.19,
      "ret_20d": 5.7
    },
    "CURE": {
      "price": 115.69,
      "change_pct": 0.1,
      "rsi10": 54.8,
      "ema9": 114.82,
      "ema20": 114.02,
      "ema50": 111.97,
      "ema200": 100.99,
      "sma50": 113.56,
      "sma200": 91.81,
      "ema_cross": "BULL",
      "above_sma200": true,
      "vs_sma200": 26.0,
      "vs_sma50": 1.9,
      "ret_1d": 0.1,
      "ret_5d": 0.17,
      "ret_10d": 4.75,
      "ret_20d": 3.52
    },
    "LABU": {
      "price": 178.27,
      "change_pct": -0.63,
      "rsi10": 58.5,
      "ema9": 170.6,
      "ema20": 168.91,
      "ema50": 163.67,
      "ema200": 126.07,
      "sma50": 167.87,
      "sma200": 106.97,
      "ema_cross": "BULL",
      "above_sma200": true,
      "vs_sma200": 66.7,
      "vs_sma50": 6.2,
      "ret_1d": -0.63,
      "ret_5d": 6.94,
      "ret_10d": 7.58,
      "ret_20d": -1.99
    },
    "DRN": {
      "price": 10.4,
      "change_pct": -1.75,
      "rsi10": 62.3,
      "ema9": 10.31,
      "ema20": 9.93,
      "ema50": 9.43,
      "ema200": 9.34,
      "sma50": 9.14,
      "sma200": 9.3,
      "ema_cross": "BULL",
      "above_sma200": true,
      "vs_sma200": 11.9,
      "vs_sma50": 13.8,
      "ret_1d": -1.75,
      "ret_5d": 0.82,
      "ret_10d": 4.05,
      "ret_20d": 15.61
    },
    "FNGO": {
      "price": 96.09,
      "change_pct": 4.03,
      "rsi10": 43.9,
      "ema9": 95.21,
      "ema20": 99.0,
      "ema50": 107.1,
      "ema200": 109.49,
      "sma50": 108.88,
      "sma200": 113.67,
      "ema_cross": "BEAR",
      "above_sma200": false,
      "vs_sma200": -15.5,
      "vs_sma50": -11.7,
      "ret_1d": 4.03,
      "ret_5d": 1.03,
      "ret_10d": -4.52,
      "ret_20d": -15.97
    },
    "HIBL": {
      "price": 75.38,
      "change_pct": 2.59,
      "rsi10": 53.1,
      "ema9": 73.95,
      "ema20": 73.75,
      "ema50": 71.56,
      "ema200": 59.02,
      "sma50": 72.45,
      "sma200": 55.81,
      "ema_cross": "BULL",
      "above_sma200": true,
      "vs_sma200": 35.1,
      "vs_sma50": 4.0,
      "ret_1d": 2.59,
      "ret_5d": -1.13,
      "ret_10d": -1.72,
      "ret_20d": 1.02
    },
    "EDC": {
      "price": 81.25,
      "change_pct": 2.48,
      "rsi10": 70.3,
      "ema9": 76.52,
      "ema20": 73.17,
      "ema50": 66.69,
      "ema200": 52.3,
      "sma50": 64.51,
      "sma200": 49.57,
      "ema_cross": "BULL",
      "above_sma200": true,
      "vs_sma200": 63.9,
      "vs_sma50": 25.9,
      "ret_1d": 2.48,
      "ret_5d": 9.29,
      "ret_10d": 11.95,
      "ret_20d": 12.62
    },
    "YINN": {
      "price": 40.69,
      "change_pct": -1.52,
      "rsi10": 36.0,
      "ema9": 42.16,
      "ema20": 43.24,
      "ema50": 44.59,
      "ema200": 43.75,
      "sma50": 44.65,
      "sma200": 45.07,
      "ema_cross": "BEAR",
      "above_sma200": false,
      "vs_sma200": -9.7,
      "vs_sma50": -8.9,
      "ret_1d": -1.52,
      "ret_5d": -4.44,
      "ret_10d": -10.49,
      "ret_20d": -14.26
    },
    "KORU": {
      "price": 595.41,
      "change_pct": 7.71,
      "rsi10": 80.1,
      "ema9": 494.41,
      "ema20": 429.27,
      "ema50": 332.62,
      "ema200": 185.29,
      "sma50": 298.71,
      "sma200": 150.22,
      "ema_cross": "BULL",
      "above_sma200": true,
      "vs_sma200": 296.4,
      "vs_sma50": 99.3,
      "ret_1d": 7.71,
      "ret_5d": 36.62,
      "ret_10d": 64.42,
      "ret_20d": 68.92
    },
    "EURL": {
      "price": 50.93,
      "change_pct": 0.79,
      "rsi10": 64.0,
      "ema9": 49.9,
      "ema20": 48.74,
      "ema50": 45.77,
      "ema200": 38.22,
      "sma50": 45.35,
      "sma200": 37.5,
      "ema_cross": "BULL",
      "above_sma200": true,
      "vs_sma200": 35.8,
      "vs_sma50": 12.3,
      "ret_1d": 0.79,
      "ret_5d": 2.17,
      "ret_10d": 3.14,
      "ret_20d": 3.2
    },
    "INDL": {
      "price": 53.26,
      "change_pct": -0.15,
      "rsi10": 45.2,
      "ema9": 53.8,
      "ema20": 53.99,
      "ema50": 54.62,
      "ema200": 56.5,
      "sma50": 54.66,
      "sma200": 57.15,
      "ema_cross": "BEAR",
      "above_sma200": false,
      "vs_sma200": -6.8,
      "vs_sma50": -2.6,
      "ret_1d": -0.15,
      "ret_5d": -2.72,
      "ret_10d": -4.42,
      "ret_20d": 2.74
    },
    "BTC-USD": {
      "price": 67583.47,
      "change_pct": 5.47,
      "rsi10": 44.9,
      "ema9": 66874.14,
      "ema20": 69313.11,
      "ema50": 76433.09,
      "ema200": 91535.23,
      "sma50": 79648.11,
      "sma200": 98161.59,
      "ema_cross": "BEAR",
      "above_sma200": false,
      "vs_sma200": -31.2,
      "vs_sma50": -15.1,
      "ret_1d": 5.47,
      "ret_5d": -0.62,
      "ret_10d": -1.75,
      "ret_20d": 7.79
    },
    "AMD": {
      "price": 211.17,
      "change_pct": -1.25,
      "rsi10": 48.9,
      "ema9": 207.51,
      "ema20": 212.91,
      "ema50": 217.72,
      "ema200": 192.93,
      "sma50": 218.97,
      "sma200": 185.62,
      "ema_cross": "BEAR",
      "above_sma200": true,
      "vs_sma200": 13.8,
      "vs_sma50": -3.6,
      "ret_1d": -1.25,
      "ret_5d": 5.52,
      "ret_10d": -1.12,
      "ret_20d": -16.21
    },
    "NVDA": {
      "price": 196.46,
      "change_pct": 1.87,
      "rsi10": 66.1,
      "ema9": 190.4,
      "ema20": 188.13,
      "ema50": 186.32,
      "ema200": 172.57,
      "sma50": 185.42,
      "sma200": 174.34,
      "ema_cross": "BULL",
      "above_sma200": true,
      "vs_sma200": 12.7,
      "vs_sma50": 6.0,
      "ret_1d": 1.87,
      "ret_5d": 4.51,
      "ret_10d": 4.2,
      "ret_20d": 4.21
    },
    "VOOV": {
      "price": 213.43,
      "change_pct": -0.12,
      "rsi10": 55.2,
      "ema9": 213.12,
      "ema20": 212.35,
      "ema50": 209.62,
      "ema200": 199.1,
      "sma50": 209.48,
      "sma200": 196.94,
      "ema_cross": "BULL",
      "above_sma200": true,
      "vs_sma200": 8.4,
      "vs_sma50": 1.9,
      "ret_1d": -0.12,
      "ret_5d": -0.06,
      "ret_10d": -0.29,
      "ret_20d": 1.9
    },
    "VOOG": {
      "price": 439.63,
      "change_pct": 1.13,
      "rsi10": 53.7,
      "ema9": 435.35,
      "ema20": 437.26,
      "ema50": 439.93,
      "ema200": 420.0,
      "sma50": 442.4,
      "sma200": 421.14,
      "ema_cross": "BEAR",
      "above_sma200": true,
      "vs_sma200": 4.4,
      "vs_sma50": -0.6,
      "ret_1d": 1.13,
      "ret_5d": 1.45,
      "ret_10d": 0.06,
      "ret_20d": -2.85
    },
    "VTV": {
      "price": 206.12,
      "change_pct": -0.02,
      "rsi10": 60.9,
      "ema9": 205.78,
      "ema20": 204.08,
      "ema50": 199.31,
      "ema200": 186.52,
      "sma50": 198.42,
      "sma200": 184.17,
      "ema_cross": "BULL",
      "above_sma200": true,
      "vs_sma200": 11.9,
      "vs_sma50": 3.9,
      "ret_1d": -0.02,
      "ret_5d": -0.21,
      "ret_10d": 0.14,
      "ret_20d": 3.99
    },
    "QQQE": {
      "price": 103.66,
      "change_pct": 0.81,
      "rsi10": 53.9,
      "ema9": 102.87,
      "ema20": 103.06,
      "ema50": 103.14,
      "ema200": 99.85,
      "sma50": 103.54,
      "sma200": 100.04,
      "ema_cross": "BEAR",
      "above_sma200": true,
      "vs_sma200": 3.6,
      "vs_sma50": 0.1,
      "ret_1d": 0.81,
      "ret_5d": 0.47,
      "ret_10d": 0.73,
      "ret_20d": -2.15
    },
    "KMLM": {
      "price": 26.92,
      "change_pct": 0.26,
      "rsi10": 62.1,
      "ema9": 26.74,
      "ema20": 26.63,
      "ema50": 26.35,
      "ema200": 25.91,
      "sma50": 26.33,
      "sma200": 25.59,
      "ema_cross": "BULL",
      "above_sma200": true,
      "vs_sma200": 5.2,
      "vs_sma50": 2.2,
      "ret_1d": 0.26,
      "ret_5d": 0.9,
      "ret_10d": 0.3,
      "ret_20d": 1.24
    },
    "DBMF": {
      "price": 31.32,
      "change_pct": 0.66,
      "rsi10": 71.3,
      "ema9": 30.79,
      "ema20": 30.31,
      "ema50": 29.4,
      "ema200": 27.19,
      "sma50": 29.2,
      "sma200": 26.48,
      "ema_cross": "BULL",
      "above_sma200": true,
      "vs_sma200": 18.3,
      "vs_sma50": 7.3,
      "ret_1d": 0.66,
      "ret_5d": 2.5,
      "ret_10d": 2.6,
      "ret_20d": 4.84
    },
    "CTA": {
      "price": 29.82,
      "change_pct": -0.17,
      "rsi10": 69.1,
      "ema9": 29.53,
      "ema20": 29.04,
      "ema50": 28.31,
      "ema200": 27.43,
      "sma50": 28.03,
      "sma200": 27.28,
      "ema_cross": "BULL",
      "above_sma200": true,
      "vs_sma200": 9.3,
      "vs_sma50": 6.4,
      "ret_1d": -0.17,
      "ret_5d": 0.88,
      "ret_10d": 3.79,
      "ret_20d": 5.15
    },
    "BTAL": {
      "price": 13.66,
      "change_pct": -1.23,
      "rsi10": 37.9,
      "ema9": 13.89,
      "ema20": 13.96,
      "ema50": 14.11,
      "ema200": 15.42,
      "sma50": 14.05,
      "sma200": 15.61,
      "ema_cross": "BEAR",
      "above_sma200": false,
      "vs_sma200": -12.5,
      "vs_sma50": -2.8,
      "ret_1d": -1.23,
      "ret_5d": -1.8,
      "ret_10d": -2.22,
      "ret_20d": -1.87
    },
    "KOLD": {
      "price": 22.74,
      "change_pct": -4.05,
      "rsi10": 50.9,
      "ema9": 22.17,
      "ema20": 22.67,
      "ema50": 26.01,
      "ema200": 31.17,
      "sma50": 29.0,
      "sma200": 29.73,
      "ema_cross": "BEAR",
      "above_sma200": false,
      "vs_sma200": -23.5,
      "vs_sma50": -21.6,
      "ret_1d": -4.05,
      "ret_5d": 2.25,
      "ret_10d": 7.47,
      "ret_20d": 20.89
    }
  }
}